netmeter
